{
  "project": "platform-v7",
  "mode": "variant-b",
  "status": "active",
  "currentStatus": "in_progress",
  "current": "MASTER-ТЗ 2 — все VP-слои (VP-1…VP-8) закрыты; остаток = owner-only действия (разблокировать Vercel, отметить web-unit required, ротация VERCEL_TOKEN, dependency graph)",
  "fullTzReadinessPercent": 69,
  "openPr": null,
  "lastClosed": [
    "baseline",
    "Runner Inline PR",
    "Runner Gate Fix",
    "Runner Opens PR",
    "Runner PR Permission Smoke",
    "Autopilot Resilience Layer",
    "Role Boundary Smoke",
    "Autopilot State Schema",
    "Autopilot Next-layer Selector",
    "Autopilot Check Analyzer",
    "Autopilot Merge Gate",
    "Autopilot Dry-run Loop",
    "Autopilot Safe Task Intake",
    "Autopilot Issue Executor Dry-run",
    "Autopilot Issue Executor PR Wiring",
    "Autopilot Full Loop Verification",
    "Autopilot Live Controlled Pilot Gate",
    "Autopilot Step Enablement",
    "Autopilot Scope Proposal Gate",
    "Autopilot Exact Path Unlock",
    "Autopilot Product Slice Proposal",
    "Autopilot Product Slice 01 through 20",
    "Stage 3: RBAC",
    "Stage 4: MoneyTree / DocMatrix / BankBasis / ActionBoundary / QA",
    "PR 5.0: Runtime Inventory",
    "PR 5.3: Persistence Ports",
    "PR 5.4: DTO / Validation",
    "PR 5.1: Application Service Layer",
    "PR 5.5: Mock Persistence Adapter",
    "PR 5.2: Server Action Wrappers",
    "PR 5.6: Runtime Integration Tests",
    "PR 5.7: Final Stage 5 QA",
    "PR 6.0: External Adapter Emulators",
    "PR 7.0: AI Integration Gateway",
    "PR 8.0: Product Entry / Onboarding",
    "PR 9.0: Theme / Visual / Role Cockpit",
    "PR 10.0: Deal Workspace",
    "PR 11.0: Deal State / Dispute / Evidence",
    "PR 12.0: Grain Execution Automation Engines",
    "PR 13.0: Domain Layer",
    "PR 14.0: Deal Transaction Layer",
    "PR 15.0: Grain Automation Engines 2",
    "PR 16.0: Risk & Document Security Layer",
    "PR 17.0: Trust & Intelligence Layer",
    "PR 18.0: Deal Execution SOT",
    "PR 19.0: Shell, Simulation & Deal360",
    "PR 20.0: Bank Payment Basis, Routes Manifest & Support Contour",
    "VP-1: Visible Execution Entry Cockpit",
    "VP-2: Runtime QA Stabilization (slice 1)",
    "VP-3: Runtime-bound Entry Cockpit",
    "VP-4: Product Entry (open, role-preview, onboarding, merged via PR #1689)",
    "VP-2.3: Shell / Role Isolation Guards",
    "VP-2.2: Server Action Route Contracts (closed in slice 1, verified green)",
    "VP-2.4: Honesty / Premium Copy Guards (named scope)",
    "VP-2.5: Remaining Tail + Regression Gate (full web vitest green)",
    "VP-8: Theme token parity (dark-theme native, light preserved)",
    "VP-5: Driver / Logistics cockpit runtime binding",
    "VP-6: Bank cockpit runtime binding",
    "VP-7: Dispute / Evidence binding"
  ],
  "lockedUntilCurrentGreen": [
    "Backend / DB / runtime persistence expansion",
    "Live integration expansion",
    "Package or lockfile changes"
  ],
  "allowedCurrentScope": [
    "apps/web/tests/unit/**",
    "apps/web/tests/setup.ts",
    "apps/web/components/v7r/**",
    "apps/web/components/platform-v7/**",
    "apps/web/app/platform-v7/**",
    "apps/web/lib/platform-v7/**",
    "apps/web/styles/**",
    "apps/web/lib/v7r/**",
    "packages/domain-core/src/execution-simulation/**",
    ".github/workflows/dependency-review.yml",
    ".github/workflows/automerge.yml",
    ".github/workflows/platform-v7-autopilot-guard.yml",
    ".github/workflows/platform-v7-autopilot-issue-executor-dry-run.yml",
    ".github/workflows/platform-v7-autopilot-executor-wiring.yml",
    ".github/workflows/web-unit.yml",
    "scripts/p7-autopilot-issue-executor-dry-run.mjs",
    "scripts/p7-autopilot-issue-executor-pr-wiring.mjs",
    "docs/platform-v7/autopilot/**",
    "docs/platform-v7/execution-queue.md",
    ".github/workflows/platform-v7-dual-hosting-smoke.yml",
    "docs/platform-v7/dual-hosting-operating-rules.md"
  ],
  "agentWritableScope": [
    "apps/web/tests/unit/**",
    "apps/web/tests/setup.ts",
    "apps/web/components/v7r/**",
    "apps/web/components/platform-v7/**",
    "apps/web/app/platform-v7/**",
    "apps/web/lib/platform-v7/**",
    "apps/web/styles/**",
    "apps/web/lib/v7r/**",
    "packages/domain-core/src/execution-simulation/**",
    ".github/workflows/dependency-review.yml",
    ".github/workflows/automerge.yml",
    ".github/workflows/platform-v7-autopilot-guard.yml",
    ".github/workflows/platform-v7-autopilot-issue-executor-dry-run.yml",
    ".github/workflows/platform-v7-autopilot-executor-wiring.yml",
    ".github/workflows/web-unit.yml",
    "scripts/p7-autopilot-issue-executor-dry-run.mjs",
    "scripts/p7-autopilot-issue-executor-pr-wiring.mjs",
    "docs/platform-v7/autopilot/**",
    "docs/platform-v7/execution-queue.md",
    ".github/workflows/platform-v7-dual-hosting-smoke.yml",
    "docs/platform-v7/dual-hosting-operating-rules.md"
  ],
  "controlledActions": {
    "enabled": true
  },
  "forbiddenZones": [
    "apps/landing",
    "apps/web/app/platform-v7",
    "apps/web/components/platform-v7",
    "apps/web/components/v7r",
    "apps/web/lib/platform-v7",
    "apps/web/app/api",
    "package.json",
    "package-lock.json",
    "pnpm-lock.yaml"
  ],
  "maturityLanguage": [
    "controlled-pilot",
    "pre-integration"
  ],
  "forbiddenClaims": [],
  "readiness": "Full web vitest GREEN 565 files / 3612 tests; web-unit required gate active. Все VP-слои MASTER-ТЗ 2 закрыты: VP-1..VP-4 (entry/QA/runtime/product), VP-2.2/2.3/2.4/2.5 (contracts/isolation/honesty/tail 330->0), VP-5/6/7 (driver/bank/dispute runtime binding, sourceMeta.runtimeBound), VP-8 (token parity тёмной темы). Визуальная система + премиум-HX + честная копия §4.2 + Empty/Skeleton/Smart Disclosure merged. Остаток = owner-only: разблокировать Vercel (account blocked), отметить web-unit required, ротация VERCEL_TOKEN, dependency graph; затем визуальный QA тёмной темы на живом Vercel."
}
